SeafileContentManager/__init__.py
SeafileContentManager/seacheckpoints.py
SeafileContentManager/seafilemixin.py
SeafileContentManager/seamanager.py
SeafileContentManager/seaopen.py
SeafileContentManager/tests/__init__.py
SeafileContentManager/tests/test_SeafileContentManager.py
SeafileContentManager-0.1.2.dist-info/LICENSE
SeafileContentManager-0.1.2.dist-info/METADATA
SeafileContentManager-0.1.2.dist-info/WHEEL
SeafileContentManager-0.1.2.dist-info/top_level.txt
SeafileContentManager-0.1.2.dist-info/RECORD
