Metadata-Version: 2.1
Name: SeafileContentManager
Version: 0.1.2
Summary: ContentManager using Seafile's WebAPI
Home-page: https://github.com/computational-antiquity/SeafileContentManager/
Author: Malte Vogl
Author-email: mvogl@mpiwg-berlin.mpg.de
License: GPLv3
Project-URL: Tracker, https://github.com/computational-antiquity/SeafileContentManager/issues
Project-URL: Download, https://github.com/computational-antiquity/SeafileContentManager/archive/0.1.1.tar.gz
Platform: UNKNOWN
Classifier: Development Status :: 3 - Alpha
Classifier: Intended Audience :: Science/Research
Classifier: Topic :: Text Processing :: General
Classifier: Topic :: Text Processing :: Indexing
Classifier: License :: OSI Approved :: GNU General Public License v3 (GPLv3)
Classifier: Programming Language :: Python :: 3
Requires-Python: >=3
Requires-Dist: jupyter
Requires-Dist: nbformat
Requires-Dist: requests
